cache.py
docgen.py
model.py
cargo_docgen-0.1.3.dist-info/licenses/LICENCE
cargo_docgen-0.1.3.dist-info/METADATA
cargo_docgen-0.1.3.dist-info/WHEEL
cargo_docgen-0.1.3.dist-info/entry_points.txt
cargo_docgen-0.1.3.dist-info/top_level.txt
cargo_docgen-0.1.3.dist-info/RECORD
