Metadata-Version: 2.4
Name: cargo-docgen
Version: 0.1.3
Summary: Add your description here
Requires-Python: ==3.11.12
License-File: LICENCE
Requires-Dist: click>=8.1.8
Requires-Dist: mirascope>=1.22.3
Requires-Dist: termcolor>=3.0.1
Requires-Dist: toml>=0.10.2
Requires-Dist: tree-sitter==0.24.0
Requires-Dist: tree-sitter-rust==0.23.0
Dynamic: license-file
